{
  "main": {
    "id": "43f50e0355cef38d",
    "type": "split",
    "children": [
      {
        "id": "9fae986b2d3499d4",
        "type": "tabs",
        "children": [
          {
            "id": "95a66c3185b3cc78",
            "type": "leaf",
            "state": {
              "type": "markdown",
              "state": {
                "file": "Informatik/Brain Computation/Brain Models/Hebbian Learning.md",
                "mode": "source",
                "source": false
              },
              "icon": "lucide-file",
              "title": "Hebbian Learning"
            }
          }
        ]
      }
    ],
    "direction": "vertical"
  },
  "left": {
    "id": "3dcb2a47d5910cae",
    "type": "split",
    "children": [
      {
        "id": "7f8c8c23e5b6687c",
        "type": "tabs",
        "children": [
          {
            "id": "097b9a58ea336072",
            "type": "leaf",
            "state": {
              "type": "file-explorer",
              "state": {
                "sortOrder": "alphabetical",
                "autoReveal": true
              },
              "icon": "lucide-folder-closed",
              "title": "Files"
            }
          },
          {
            "id": "67d43403474fe91c",
            "type": "leaf",
            "state": {
              "type": "search",
              "state": {
                "query": "Jacob",
                "matchingCase": false,
                "explainSearch": false,
                "collapseAll": false,
                "extraContext": false,
                "sortOrder": "alphabetical"
              },
              "icon": "lucide-search",
              "title": "Search"
            }
          }
        ]
      }
    ],
    "direction": "horizontal",
    "width": 286.5
  },
  "right": {
    "id": "d1219e90b492538d",
    "type": "split",
    "children": [
      {
        "id": "9b15b79a4b78ad38",
        "type": "tabs",
        "children": [
          {
            "id": "5e40097f8861998e",
            "type": "leaf",
            "state": {
              "type": "backlink",
              "state": {
                "file": "Science, Technology and Society/Sociology of Science/Public Understanding of Science.md",
                "collapseAll": false,
                "extraContext": false,
                "sortOrder": "alphabetical",
                "showSearch": false,
                "searchQuery": "",
                "backlinkCollapsed": false,
                "unlinkedCollapsed": true
              },
              "icon": "links-coming-in",
              "title": "Backlinks for Public Understanding of Science"
            }
          }
        ]
      }
    ],
    "direction": "horizontal",
    "width": 322,
    "collapsed": true
  },
  "left-ribbon": {
    "hiddenItems": {
      "switcher:Open quick switcher": false,
      "graph:Open graph view": false,
      "command-palette:Open command palette": false
    }
  },
  "active": "95a66c3185b3cc78",
  "lastOpenFiles": [
    "Informatik/Brain Computation/Brain Models/Tsodyks Synapse Model.md",
    "Informatik/Brain Computation/Brain Models/Hebbian Learning.md",
    "Informatik/Brain Computation/Neurons/Plasticity.md",
    "Informatik/Brain Computation/Neurons/Neurons.md",
    "Informatik/Brain Computation/Neurons/Synapses.md",
    "Informatik/Brain Computation/Neurons/Synaptic Transmission.md",
    "Informatik/Brain Computation/Neurons/Spike Generation.md",
    "Informatik/Brain Computation/Neurons/Dendrites.md",
    "Mathematik/Wahrscheinlichkeitstheorie/Wahrscheinlichkeitsverteilungen/Poisson Verteilung.md",
    "Informatik/Brain Computation/Brain Models/Synaptic Models.md",
    "z_images/Pasted image 20250617095124.png",
    "z_images/Pasted image 20250617095008.png",
    "z_images/Pasted image 20250617094947.png",
    "Informatik/Brain Computation/Computation/Computation.md",
    "Informatik/Brain Computation/Brain Models/Brain Models.md",
    "Informatik/Brain Computation/Brain Models/Exponential Integrate-And-Fire Model.md",
    "Informatik/Brain Computation/Brain Models/Adaptive Exponential Integrate-And-Fire Model.md",
    "Informatik/Brain Computation/Brain Models/Dynamical Systems.md",
    "Informatik/Machine Learning/Retrieval Augmented Generation/Notes.md",
    "Informatik/Machine Learning/Machine Learning.md",
    "Informatik/Brain Computation/Brain Anatomy.md",
    "Informatik/Brain Computation/Brain Computation.md",
    "Informatik/Data Science and AI/Data Science and AI.md",
    "Informatik/Data Science and AI/Machine Learning/Artificial Neural Networks.md",
    "Informatik/Brain Computation/Computation/Spiking Neural Networks.md",
    "Mathematik/Physik/Physik.md",
    "Mathematik/Statistik/Computational Methods/Bonferroni Correction.md",
    "Mathematik/Allgemeine Mathematik/Untitled.md",
    "Informatik/Brain Computation/Brain Models/Nonlinear Integrate-And-Fire Models.md",
    "Informatik/Machine Learning/Brain Computation/Untitled",
    "z_images/Pasted image 20250616151154.png",
    "z_images/Pasted image 20250616140856.png",
    "z_images/Pasted image 20250616140840.png",
    "z_images/Pasted image 20250616130944.png",
    "z_images/Pasted image 20250616130931.png",
    "z_images/Pasted image 20250616130918.png",
    "z_images/Pasted image 20250616122352.png",
    "Informatik/Machine Learning/Brain Computation/Neurons/Untitled",
    "Informatik/Brain Computation/Neurons",
    "Informatik/Brain Computation/Computation",
    "Informatik/Machine Learning/ML1/lecture07.pdf",
    "Informatik/Machine Learning/ML1/lecture06.pdf",
    "Informatik/Machine Learning/ML1/lecture08.pdf",
    "Informatik/Machine Learning/ML1/lecture10.pdf",
    "Informatik/Machine Learning/ML1/lecture09.pdf",
    "Informatik/Machine Learning/ML1/lecture11.pdf",
    "Informatik/Untitled.canvas",
    "Untitled.canvas"
  ]
}